src/__init__.py
demo_0.0.1-0.0.1.dist-info/METADATA
demo_0.0.1-0.0.1.dist-info/WHEEL
demo_0.0.1-0.0.1.dist-info/entry_points.txt
demo_0.0.1-0.0.1.dist-info/top_level.txt
demo_0.0.1-0.0.1.dist-info/RECORD
